MANIFEST.in
README.rst
setup.cfg
setup.py
collective/__init__.py
collective.takeaportrait.egg-info/PKG-INFO
collective.takeaportrait.egg-info/SOURCES.txt
collective.takeaportrait.egg-info/dependency_links.txt
collective.takeaportrait.egg-info/entry_points.txt
collective.takeaportrait.egg-info/namespace_packages.txt
collective.takeaportrait.egg-info/not-zip-safe
collective.takeaportrait.egg-info/requires.txt
collective.takeaportrait.egg-info/top_level.txt
collective/takeaportrait/__init__.py
collective/takeaportrait/configure.zcml
collective/takeaportrait/interfaces.py
collective/takeaportrait/browser/__init__.py
collective/takeaportrait/browser/configure.zcml
collective/takeaportrait/browser/view.py
collective/takeaportrait/browser/resources/close.png
collective/takeaportrait/browser/resources/ok.png
collective/takeaportrait/browser/resources/repeat.png
collective/takeaportrait/browser/resources/take-portrait.js
collective/takeaportrait/browser/resources/web_camera.png
collective/takeaportrait/locales/collective.takeaportrait-manual.pot
collective/takeaportrait/locales/collective.takeaportrait.pot
collective/takeaportrait/locales/rebuildPo.sh
collective/takeaportrait/locales/it/LC_MESSAGES/collective.takeaportrait.po
collective/takeaportrait/opencv/__init__.py
collective/takeaportrait/opencv/configure.zcml
collective/takeaportrait/opencv/face_detection.py
collective/takeaportrait/opencv/haarcascade_frontalface_alt.xml
collective/takeaportrait/profiles/default/browserlayer.xml
collective/takeaportrait/profiles/default/jsregistry.xml
collective/takeaportrait/profiles/default/metadata.xml
docs/HISTORY.txt
docs/IMAGE-LICENCE.txt
docs/INSTALL.txt
docs/LICENSE.GPL
docs/LICENSE.txt