Metadata-Version: 1.1
Name: collective.takeaportrait
Version: 0.2.0
Summary: Plone site members can change personal portrait using a webcam
Home-page: http://plone.org/products/collective.takeaportrait
Author: keul
Author-email: luca@keul.it
License: GPL
Keywords: plone webcam portrait media-capture-api
Platform: UNKNOWN
Classifier: Development Status :: 3 - Alpha
Classifier: Framework :: Plone
Classifier: Framework :: Plone :: 4.3
Classifier: Programming Language :: Python
Classifier: Programming Language :: JavaScript
